{
  "__type__": "sp.SkeletonData",
  "_name": "LHD_longying_guang",
  "_skeletonJson": {
    "skeleton": {
      "hash": "lSbZ8gdteCqDYplWm9RDrnkGVp8",
      "spine": "3.6.53",
      "width": 524.32,
      "height": 524.32,
      "images": "./image/"
    },
    "bones": [
      {
        "name": "root"
      },
      {
        "name": "long",
        "parent": "root",
        "y": 29.84,
        "scaleX": 1.837,
        "scaleY": 1.837
      }
    ],
    "slots": [
      {
        "name": "long/1",
        "bone": "long",
        "attachment": "long/41",
        "blend": "screen"
      }
    ],
    "skins": {
      "default": {
        "long/1": {
          "long/1": {
            "type": "mesh",
            "uvs": [
              1,
              1,
              0,
              1,
              0,
              0,
              1,
              0
            ],
            "triangles": [
              1,
              2,
              3,
              1,
              3,
              0
            ],
            "vertices": [
              104.01,
              -129.19,
              -117.99,
              -129.19,
              -118,
              92.81,
              104.01,
              92.81
            ],
            "hull": 4,
            "edges": [
              0,
              2,
              2,
              4,
              4,
              6,
              0,
              6
            ],
            "width": 111,
            "height": 111
          },
          "long/2": {
            "type": "mesh",
            "uvs": [
              1,
              1,
              0,
              1,
              0,
              0,
              1,
              0
            ],
            "triangles": [
              1,
              2,
              3,
              1,
              3,
              0
            ],
            "vertices": [
              104,
              -129.19,
              -118,
              -129.19,
              -118,
              92.81,
              104,
              92.81
            ],
            "hull": 4,
            "edges": [
              0,
              2,
              2,
              4,
              4,
              6,
              0,
              6
            ],
            "width": 111,
            "height": 111
          },
          "long/3": {
            "type": "mesh",
            "uvs": [
              1,
              1,
              0,
              1,
              0,
              0,
              1,
              0
            ],
            "triangles": [
              1,
              2,
              3,
              1,
              3,
              0
            ],
            "vertices": [
              104,
              -129.19,
              -118,
              -129.19,
              -118,
              92.81,
              104,
              92.81
            ],
            "hull": 4,
            "edges": [
              0,
              2,
              2,
              4,
              4,
              6,
              0,
              6
            ],
            "width": 111,
            "height": 111
          },
          "long/4": {
            "type": "mesh",
            "uvs": [
              1,
              1,
              0,
              1,
              0,
              0,
              1,
              0
            ],
            "triangles": [
              1,
              2,
              3,
              1,
              3,
              0
            ],
            "vertices": [
              104,
              -129.19,
              -118,
              -129.19,
              -118,
              92.81,
              104,
              92.81
            ],
            "hull": 4,
            "edges": [
              0,
              2,
              2,
              4,
              4,
              6,
              0,
              6
            ],
            "width": 111,
            "height": 111
          },
          "long/5": {
            "type": "mesh",
            "uvs": [
              1,
              1,
              0,
              1,
              0,
              0,
              1,
              0
            ],
            "triangles": [
              1,
              2,
              3,
              1,
              3,
              0
            ],
            "vertices": [
              104,
              -129.19,
              -118,
              -129.19,
              -118,
              92.81,
              104,
              92.81
            ],
            "hull": 4,
            "edges": [
              0,
              2,
              2,
              4,
              4,
              6,
              0,
              6
            ],
            "width": 111,
            "height": 111
          },
          "long/6": {
            "type": "mesh",
            "uvs": [
              1,
              1,
              0,
              1,
              0,
              0,
              1,
              0
            ],
            "triangles": [
              1,
              2,
              3,
              1,
              3,
              0
            ],
            "vertices": [
              104,
              -129.19,
              -118,
              -129.19,
              -118,
              92.81,
              104,
              92.81
            ],
            "hull": 4,
            "edges": [
              0,
              2,
              2,
              4,
              4,
              6,
              0,
              6
            ],
            "width": 111,
            "height": 111
          },
          "long/7": {
            "type": "mesh",
            "uvs": [
              1,
              1,
              0,
              1,
              0,
              0,
              1,
              0
            ],
            "triangles": [
              1,
              2,
              3,
              1,
              3,
              0
            ],
            "vertices": [
              104,
              -129.19,
              -118,
              -129.19,
              -118,
              92.81,
              104,
              92.81
            ],
            "hull": 4,
            "edges": [
              0,
              2,
              2,
              4,
              4,
              6,
              0,
              6
            ],
            "width": 111,
            "height": 111
          },
          "long/8": {
            "type": "mesh",
            "uvs": [
              1,
              1,
              0,
              1,
              0,
              0,
              1,
              0
            ],
            "triangles": [
              1,
              2,
              3,
              1,
              3,
              0
            ],
            "vertices": [
              104,
              -129.19,
              -118,
              -129.19,
              -118,
              92.81,
              104,
              92.81
            ],
            "hull": 4,
            "edges": [
              0,
              2,
              2,
              4,
              4,
              6,
              0,
              6
            ],
            "width": 111,
            "height": 111
          },
          "long/9": {
            "type": "mesh",
            "uvs": [
              1,
              1,
              0,
              1,
              0,
              0,
              1,
              0
            ],
            "triangles": [
              1,
              2,
              3,
              1,
              3,
              0
            ],
            "vertices": [
              104,
              -129.19,
              -118,
              -129.19,
              -118,
              92.81,
              104,
              92.81
            ],
            "hull": 4,
            "edges": [
              0,
              2,
              2,
              4,
              4,
              6,
              0,
              6
            ],
            "width": 111,
            "height": 111
          },
          "long/10": {
            "type": "mesh",
            "uvs": [
              1,
              1,
              0,
              1,
              0,
              0,
              1,
              0
            ],
            "triangles": [
              1,
              2,
              3,
              1,
              3,
              0
            ],
            "vertices": [
              104,
              -129.19,
              -118,
              -129.19,
              -118,
              92.81,
              104,
              92.81
            ],
            "hull": 4,
            "edges": [
              0,
              2,
              2,
              4,
              4,
              6,
              0,
              6
            ],
            "width": 111,
            "height": 111
          },
          "long/11": {
            "type": "mesh",
            "uvs": [
              1,
              1,
              0,
              1,
              0,
              0,
              1,
              0
            ],
            "triangles": [
              1,
              2,
              3,
              1,
              3,
              0
            ],
            "vertices": [
              104,
              -129.19,
              -118,
              -129.19,
              -118,
              92.81,
              104,
              92.81
            ],
            "hull": 4,
            "edges": [
              0,
              2,
              2,
              4,
              4,
              6,
              0,
              6
            ],
            "width": 111,
            "height": 111
          },
          "long/12": {
            "type": "mesh",
            "uvs": [
              1,
              1,
              0,
              1,
              0,
              0,
              1,
              0
            ],
            "triangles": [
              1,
              2,
              3,
              1,
              3,
              0
            ],
            "vertices": [
              104,
              -129.19,
              -118,
              -129.19,
              -118,
              92.81,
              104,
              92.81
            ],
            "hull": 4,
            "edges": [
              0,
              2,
              2,
              4,
              4,
              6,
              0,
              6
            ],
            "width": 111,
            "height": 111
          },
          "long/13": {
            "type": "mesh",
            "uvs": [
              1,
              1,
              0,
              1,
              0,
              0,
              1,
              0
            ],
            "triangles": [
              1,
              2,
              3,
              1,
              3,
              0
            ],
            "vertices": [
              104,
              -129.19,
              -118,
              -129.19,
              -118,
              92.81,
              104,
              92.81
            ],
            "hull": 4,
            "edges": [
              0,
              2,
              2,
              4,
              4,
              6,
              0,
              6
            ],
            "width": 111,
            "height": 111
          },
          "long/14": {
            "type": "mesh",
            "uvs": [
              1,
              1,
              0,
              1,
              0,
              0,
              1,
              0
            ],
            "triangles": [
              1,
              2,
              3,
              1,
              3,
              0
            ],
            "vertices": [
              104,
              -129.19,
              -118,
              -129.19,
              -118,
              92.81,
              104,
              92.81
            ],
            "hull": 4,
            "edges": [
              0,
              2,
              2,
              4,
              4,
              6,
              0,
              6
            ],
            "width": 111,
            "height": 111
          },
          "long/15": {
            "type": "mesh",
            "uvs": [
              1,
              1,
              0,
              1,
              0,
              0,
              1,
              0
            ],
            "triangles": [
              1,
              2,
              3,
              1,
              3,
              0
            ],
            "vertices": [
              104,
              -129.19,
              -118,
              -129.19,
              -118,
              92.81,
              104,
              92.81
            ],
            "hull": 4,
            "edges": [
              0,
              2,
              2,
              4,
              4,
              6,
              0,
              6
            ],
            "width": 111,
            "height": 111
          },
          "long/16": {
            "type": "mesh",
            "uvs": [
              1,
              1,
              0,
              1,
              0,
              0,
              1,
              0
            ],
            "triangles": [
              1,
              2,
              3,
              1,
              3,
              0
            ],
            "vertices": [
              104,
              -129.19,
              -118,
              -129.19,
              -118,
              92.81,
              104,
              92.81
            ],
            "hull": 4,
            "edges": [
              0,
              2,
              2,
              4,
              4,
              6,
              0,
              6
            ],
            "width": 111,
            "height": 111
          },
          "long/17": {
            "type": "mesh",
            "uvs": [
              1,
              1,
              0,
              1,
              0,
              0,
              1,
              0
            ],
            "triangles": [
              1,
              2,
              3,
              1,
              3,
              0
            ],
            "vertices": [
              104,
              -129.19,
              -118,
              -129.19,
              -118,
              92.81,
              104,
              92.81
            ],
            "hull": 4,
            "edges": [
              0,
              2,
              2,
              4,
              4,
              6,
              0,
              6
            ],
            "width": 111,
            "height": 111
          },
          "long/18": {
            "type": "mesh",
            "uvs": [
              1,
              1,
              0,
              1,
              0,
              0,
              1,
              0
            ],
            "triangles": [
              1,
              2,
              3,
              1,
              3,
              0
            ],
            "vertices": [
              104,
              -129.19,
              -118,
              -129.19,
              -118,
              92.81,
              104,
              92.81
            ],
            "hull": 4,
            "edges": [
              0,
              2,
              2,
              4,
              4,
              6,
              0,
              6
            ],
            "width": 111,
            "height": 111
          },
          "long/19": {
            "type": "mesh",
            "uvs": [
              1,
              1,
              0,
              1,
              0,
              0,
              1,
              0
            ],
            "triangles": [
              1,
              2,
              3,
              1,
              3,
              0
            ],
            "vertices": [
              104,
              -129.19,
              -118,
              -129.19,
              -118,
              92.81,
              104,
              92.81
            ],
            "hull": 4,
            "edges": [
              0,
              2,
              2,
              4,
              4,
              6,
              0,
              6
            ],
            "width": 111,
            "height": 111
          },
          "long/20": {
            "type": "mesh",
            "uvs": [
              1,
              1,
              0,
              1,
              0,
              0,
              1,
              0
            ],
            "triangles": [
              1,
              2,
              3,
              1,
              3,
              0
            ],
            "vertices": [
              104,
              -129.19,
              -118,
              -129.19,
              -118,
              92.81,
              104,
              92.81
            ],
            "hull": 4,
            "edges": [
              0,
              2,
              2,
              4,
              4,
              6,
              0,
              6
            ],
            "width": 111,
            "height": 111
          },
          "long/21": {
            "type": "mesh",
            "uvs": [
              1,
              1,
              0,
              1,
              0,
              0,
              1,
              0
            ],
            "triangles": [
              1,
              2,
              3,
              1,
              3,
              0
            ],
            "vertices": [
              104,
              -129.19,
              -118,
              -129.19,
              -118,
              92.81,
              104,
              92.81
            ],
            "hull": 4,
            "edges": [
              0,
              2,
              2,
              4,
              4,
              6,
              0,
              6
            ],
            "width": 111,
            "height": 111
          },
          "long/22": {
            "type": "mesh",
            "uvs": [
              1,
              1,
              0,
              1,
              0,
              0,
              1,
              0
            ],
            "triangles": [
              1,
              2,
              3,
              1,
              3,
              0
            ],
            "vertices": [
              104,
              -129.19,
              -118,
              -129.19,
              -118,
              92.81,
              104,
              92.81
            ],
            "hull": 4,
            "edges": [
              0,
              2,
              2,
              4,
              4,
              6,
              0,
              6
            ],
            "width": 111,
            "height": 111
          },
          "long/23": {
            "type": "mesh",
            "uvs": [
              1,
              1,
              0,
              1,
              0,
              0,
              1,
              0
            ],
            "triangles": [
              1,
              2,
              3,
              1,
              3,
              0
            ],
            "vertices": [
              104,
              -129.19,
              -118,
              -129.19,
              -118,
              92.81,
              104,
              92.81
            ],
            "hull": 4,
            "edges": [
              0,
              2,
              2,
              4,
              4,
              6,
              0,
              6
            ],
            "width": 111,
            "height": 111
          },
          "long/24": {
            "type": "mesh",
            "uvs": [
              1,
              1,
              0,
              1,
              0,
              0,
              1,
              0
            ],
            "triangles": [
              1,
              2,
              3,
              1,
              3,
              0
            ],
            "vertices": [
              104,
              -129.19,
              -118,
              -129.19,
              -118,
              92.81,
              104,
              92.81
            ],
            "hull": 4,
            "edges": [
              0,
              2,
              2,
              4,
              4,
              6,
              0,
              6
            ],
            "width": 111,
            "height": 111
          },
          "long/25": {
            "type": "mesh",
            "uvs": [
              1,
              1,
              0,
              1,
              0,
              0,
              1,
              0
            ],
            "triangles": [
              1,
              2,
              3,
              1,
              3,
              0
            ],
            "vertices": [
              104,
              -129.19,
              -118,
              -129.19,
              -118,
              92.81,
              104,
              92.81
            ],
            "hull": 4,
            "edges": [
              0,
              2,
              2,
              4,
              4,
              6,
              0,
              6
            ],
            "width": 111,
            "height": 111
          },
          "long/26": {
            "type": "mesh",
            "uvs": [
              1,
              1,
              0,
              1,
              0,
              0,
              1,
              0
            ],
            "triangles": [
              1,
              2,
              3,
              1,
              3,
              0
            ],
            "vertices": [
              104,
              -129.19,
              -118,
              -129.19,
              -118,
              92.81,
              104,
              92.81
            ],
            "hull": 4,
            "edges": [
              0,
              2,
              2,
              4,
              4,
              6,
              0,
              6
            ],
            "width": 111,
            "height": 111
          },
          "long/27": {
            "type": "mesh",
            "uvs": [
              1,
              1,
              0,
              1,
              0,
              0,
              1,
              0
            ],
            "triangles": [
              1,
              2,
              3,
              1,
              3,
              0
            ],
            "vertices": [
              104,
              -129.19,
              -118,
              -129.19,
              -118,
              92.81,
              104,
              92.81
            ],
            "hull": 4,
            "edges": [
              0,
              2,
              2,
              4,
              4,
              6,
              0,
              6
            ],
            "width": 111,
            "height": 111
          },
          "long/28": {
            "type": "mesh",
            "uvs": [
              1,
              1,
              0,
              1,
              0,
              0,
              1,
              0
            ],
            "triangles": [
              1,
              2,
              3,
              1,
              3,
              0
            ],
            "vertices": [
              104,
              -129.19,
              -118,
              -129.19,
              -118,
              92.81,
              104,
              92.81
            ],
            "hull": 4,
            "edges": [
              0,
              2,
              2,
              4,
              4,
              6,
              0,
              6
            ],
            "width": 111,
            "height": 111
          },
          "long/29": {
            "type": "mesh",
            "uvs": [
              1,
              1,
              0,
              1,
              0,
              0,
              1,
              0
            ],
            "triangles": [
              1,
              2,
              3,
              1,
              3,
              0
            ],
            "vertices": [
              104,
              -129.19,
              -118,
              -129.19,
              -118,
              92.81,
              104,
              92.81
            ],
            "hull": 4,
            "edges": [
              0,
              2,
              2,
              4,
              4,
              6,
              0,
              6
            ],
            "width": 111,
            "height": 111
          },
          "long/30": {
            "type": "mesh",
            "uvs": [
              1,
              1,
              0,
              1,
              0,
              0,
              1,
              0
            ],
            "triangles": [
              1,
              2,
              3,
              1,
              3,
              0
            ],
            "vertices": [
              104,
              -129.19,
              -118,
              -129.19,
              -118,
              92.81,
              104,
              92.81
            ],
            "hull": 4,
            "edges": [
              0,
              2,
              2,
              4,
              4,
              6,
              0,
              6
            ],
            "width": 111,
            "height": 111
          },
          "long/31": {
            "type": "mesh",
            "uvs": [
              1,
              1,
              0,
              1,
              0,
              0,
              1,
              0
            ],
            "triangles": [
              1,
              2,
              3,
              1,
              3,
              0
            ],
            "vertices": [
              104,
              -129.19,
              -118,
              -129.19,
              -118,
              92.81,
              104,
              92.81
            ],
            "hull": 4,
            "edges": [
              0,
              2,
              2,
              4,
              4,
              6,
              0,
              6
            ],
            "width": 111,
            "height": 111
          },
          "long/32": {
            "type": "mesh",
            "uvs": [
              1,
              1,
              0,
              1,
              0,
              0,
              1,
              0
            ],
            "triangles": [
              1,
              2,
              3,
              1,
              3,
              0
            ],
            "vertices": [
              104,
              -129.19,
              -118,
              -129.19,
              -118,
              92.81,
              104,
              92.81
            ],
            "hull": 4,
            "edges": [
              0,
              2,
              2,
              4,
              4,
              6,
              0,
              6
            ],
            "width": 111,
            "height": 111
          },
          "long/33": {
            "type": "mesh",
            "uvs": [
              1,
              1,
              0,
              1,
              0,
              0,
              1,
              0
            ],
            "triangles": [
              1,
              2,
              3,
              1,
              3,
              0
            ],
            "vertices": [
              104,
              -129.19,
              -118,
              -129.19,
              -118,
              92.81,
              104,
              92.81
            ],
            "hull": 4,
            "edges": [
              0,
              2,
              2,
              4,
              4,
              6,
              0,
              6
            ],
            "width": 111,
            "height": 111
          },
          "long/34": {
            "type": "mesh",
            "uvs": [
              1,
              1,
              0,
              1,
              0,
              0,
              1,
              0
            ],
            "triangles": [
              1,
              2,
              3,
              1,
              3,
              0
            ],
            "vertices": [
              104,
              -129.19,
              -118,
              -129.19,
              -118,
              92.81,
              104,
              92.81
            ],
            "hull": 4,
            "edges": [
              0,
              2,
              2,
              4,
              4,
              6,
              0,
              6
            ],
            "width": 111,
            "height": 111
          },
          "long/35": {
            "type": "mesh",
            "uvs": [
              1,
              1,
              0,
              1,
              0,
              0,
              1,
              0
            ],
            "triangles": [
              1,
              2,
              3,
              1,
              3,
              0
            ],
            "vertices": [
              104,
              -129.19,
              -118,
              -129.19,
              -118,
              92.81,
              104,
              92.81
            ],
            "hull": 4,
            "edges": [
              0,
              2,
              2,
              4,
              4,
              6,
              0,
              6
            ],
            "width": 111,
            "height": 111
          },
          "long/36": {
            "type": "mesh",
            "uvs": [
              1,
              1,
              0,
              1,
              0,
              0,
              1,
              0
            ],
            "triangles": [
              1,
              2,
              3,
              1,
              3,
              0
            ],
            "vertices": [
              104,
              -129.19,
              -118,
              -129.19,
              -118,
              92.81,
              104,
              92.81
            ],
            "hull": 4,
            "edges": [
              0,
              2,
              2,
              4,
              4,
              6,
              0,
              6
            ],
            "width": 111,
            "height": 111
          },
          "long/37": {
            "type": "mesh",
            "uvs": [
              1,
              1,
              0,
              1,
              0,
              0,
              1,
              0
            ],
            "triangles": [
              1,
              2,
              3,
              1,
              3,
              0
            ],
            "vertices": [
              104,
              -129.19,
              -118,
              -129.19,
              -118,
              92.81,
              104,
              92.81
            ],
            "hull": 4,
            "edges": [
              0,
              2,
              2,
              4,
              4,
              6,
              0,
              6
            ],
            "width": 111,
            "height": 111
          },
          "long/38": {
            "type": "mesh",
            "uvs": [
              1,
              1,
              0,
              1,
              0,
              0,
              1,
              0
            ],
            "triangles": [
              1,
              2,
              3,
              1,
              3,
              0
            ],
            "vertices": [
              104,
              -129.19,
              -118,
              -129.19,
              -118,
              92.81,
              104,
              92.81
            ],
            "hull": 4,
            "edges": [
              0,
              2,
              2,
              4,
              4,
              6,
              0,
              6
            ],
            "width": 111,
            "height": 111
          },
          "long/39": {
            "type": "mesh",
            "uvs": [
              1,
              1,
              0,
              1,
              0,
              0,
              1,
              0
            ],
            "triangles": [
              1,
              2,
              3,
              1,
              3,
              0
            ],
            "vertices": [
              104,
              -129.19,
              -118,
              -129.19,
              -118,
              92.81,
              104,
              92.81
            ],
            "hull": 4,
            "edges": [
              0,
              2,
              2,
              4,
              4,
              6,
              0,
              6
            ],
            "width": 111,
            "height": 111
          },
          "long/40": {
            "type": "mesh",
            "uvs": [
              1,
              1,
              0,
              1,
              0,
              0,
              1,
              0
            ],
            "triangles": [
              1,
              2,
              3,
              1,
              3,
              0
            ],
            "vertices": [
              104,
              -129.19,
              -118,
              -129.19,
              -118,
              92.81,
              104,
              92.81
            ],
            "hull": 4,
            "edges": [
              0,
              2,
              2,
              4,
              4,
              6,
              0,
              6
            ],
            "width": 111,
            "height": 111
          },
          "long/41": {
            "type": "mesh",
            "uvs": [
              1,
              1,
              0,
              1,
              0,
              0,
              1,
              0
            ],
            "triangles": [
              1,
              2,
              3,
              1,
              3,
              0
            ],
            "vertices": [
              104,
              -129.19,
              -118,
              -129.19,
              -118,
              92.81,
              104,
              92.81
            ],
            "hull": 4,
            "edges": [
              0,
              2,
              2,
              4,
              4,
              6,
              0,
              6
            ],
            "width": 111,
            "height": 111
          }
        }
      }
    },
    "animations": {
      "animation": {
        "slots": {
          "long/1": {
            "color": [
              {
                "time": 1.1667,
                "color": "ffffffff"
              },
              {
                "time": 1.3333,
                "color": "ffffff00"
              }
            ],
            "attachment": [
              {
                "time": 0,
                "name": "long/1"
              },
              {
                "time": 0.0333,
                "name": "long/2"
              },
              {
                "time": 0.0667,
                "name": "long/3"
              },
              {
                "time": 0.1,
                "name": "long/4"
              },
              {
                "time": 0.1333,
                "name": "long/5"
              },
              {
                "time": 0.1667,
                "name": "long/6"
              },
              {
                "time": 0.2,
                "name": "long/7"
              },
              {
                "time": 0.2333,
                "name": "long/8"
              },
              {
                "time": 0.2667,
                "name": "long/9"
              },
              {
                "time": 0.3,
                "name": "long/10"
              },
              {
                "time": 0.3333,
                "name": "long/11"
              },
              {
                "time": 0.3667,
                "name": "long/12"
              },
              {
                "time": 0.4,
                "name": "long/13"
              },
              {
                "time": 0.4333,
                "name": "long/14"
              },
              {
                "time": 0.4667,
                "name": "long/15"
              },
              {
                "time": 0.5,
                "name": "long/16"
              },
              {
                "time": 0.5333,
                "name": "long/17"
              },
              {
                "time": 0.5667,
                "name": "long/18"
              },
              {
                "time": 0.6,
                "name": "long/19"
              },
              {
                "time": 0.6333,
                "name": "long/20"
              },
              {
                "time": 0.6667,
                "name": "long/21"
              },
              {
                "time": 0.7,
                "name": "long/22"
              },
              {
                "time": 0.7333,
                "name": "long/23"
              },
              {
                "time": 0.7667,
                "name": "long/24"
              },
              {
                "time": 0.8,
                "name": "long/25"
              },
              {
                "time": 0.8333,
                "name": "long/26"
              },
              {
                "time": 0.8667,
                "name": "long/27"
              },
              {
                "time": 0.9,
                "name": "long/28"
              },
              {
                "time": 0.9333,
                "name": "long/29"
              },
              {
                "time": 0.9667,
                "name": "long/30"
              },
              {
                "time": 1,
                "name": "long/31"
              },
              {
                "time": 1.0333,
                "name": "long/32"
              },
              {
                "time": 1.0667,
                "name": "long/33"
              },
              {
                "time": 1.1,
                "name": "long/34"
              },
              {
                "time": 1.1333,
                "name": "long/35"
              },
              {
                "time": 1.1667,
                "name": "long/36"
              },
              {
                "time": 1.2,
                "name": "long/37"
              },
              {
                "time": 1.2333,
                "name": "long/38"
              },
              {
                "time": 1.2667,
                "name": "long/39"
              },
              {
                "time": 1.3,
                "name": "long/40"
              },
              {
                "time": 1.3333,
                "name": "long/41"
              }
            ]
          }
        }
      }
    }
  },
  "_atlasText": "\nLHD_longying_guang.png\nsize: 1024,1024\nformat: RGBA8888\nfilter: Linear,Linear\nrepeat: none\nlong/1\n  rotate: false\n  xy: 2, 906\n  size: 111, 111\n  orig: 111, 111\n  offset: 0, 0\n  index: -1\nlong/10\n  rotate: false\n  xy: 341, 906\n  size: 111, 111\n  orig: 111, 111\n  offset: 0, 0\n  index: -1\nlong/11\n  rotate: false\n  xy: 2, 454\n  size: 111, 111\n  orig: 111, 111\n  offset: 0, 0\n  index: -1\nlong/12\n  rotate: false\n  xy: 115, 567\n  size: 111, 111\n  orig: 111, 111\n  offset: 0, 0\n  index: -1\nlong/13\n  rotate: false\n  xy: 228, 680\n  size: 111, 111\n  orig: 111, 111\n  offset: 0, 0\n  index: -1\nlong/14\n  rotate: false\n  xy: 341, 793\n  size: 111, 111\n  orig: 111, 111\n  offset: 0, 0\n  index: -1\nlong/15\n  rotate: false\n  xy: 454, 906\n  size: 111, 111\n  orig: 111, 111\n  offset: 0, 0\n  index: -1\nlong/16\n  rotate: false\n  xy: 2, 341\n  size: 111, 111\n  orig: 111, 111\n  offset: 0, 0\n  index: -1\nlong/17\n  rotate: false\n  xy: 115, 454\n  size: 111, 111\n  orig: 111, 111\n  offset: 0, 0\n  index: -1\nlong/18\n  rotate: false\n  xy: 228, 567\n  size: 111, 111\n  orig: 111, 111\n  offset: 0, 0\n  index: -1\nlong/19\n  rotate: false\n  xy: 341, 680\n  size: 111, 111\n  orig: 111, 111\n  offset: 0, 0\n  index: -1\nlong/2\n  rotate: false\n  xy: 2, 793\n  size: 111, 111\n  orig: 111, 111\n  offset: 0, 0\n  index: -1\nlong/20\n  rotate: false\n  xy: 454, 793\n  size: 111, 111\n  orig: 111, 111\n  offset: 0, 0\n  index: -1\nlong/21\n  rotate: false\n  xy: 567, 906\n  size: 111, 111\n  orig: 111, 111\n  offset: 0, 0\n  index: -1\nlong/22\n  rotate: false\n  xy: 2, 228\n  size: 111, 111\n  orig: 111, 111\n  offset: 0, 0\n  index: -1\nlong/23\n  rotate: false\n  xy: 115, 341\n  size: 111, 111\n  orig: 111, 111\n  offset: 0, 0\n  index: -1\nlong/24\n  rotate: false\n  xy: 228, 454\n  size: 111, 111\n  orig: 111, 111\n  offset: 0, 0\n  index: -1\nlong/25\n  rotate: false\n  xy: 341, 567\n  size: 111, 111\n  orig: 111, 111\n  offset: 0, 0\n  index: -1\nlong/26\n  rotate: false\n  xy: 454, 680\n  size: 111, 111\n  orig: 111, 111\n  offset: 0, 0\n  index: -1\nlong/27\n  rotate: false\n  xy: 567, 793\n  size: 111, 111\n  orig: 111, 111\n  offset: 0, 0\n  index: -1\nlong/28\n  rotate: false\n  xy: 680, 906\n  size: 111, 111\n  orig: 111, 111\n  offset: 0, 0\n  index: -1\nlong/29\n  rotate: false\n  xy: 2, 115\n  size: 111, 111\n  orig: 111, 111\n  offset: 0, 0\n  index: -1\nlong/3\n  rotate: false\n  xy: 115, 906\n  size: 111, 111\n  orig: 111, 111\n  offset: 0, 0\n  index: -1\nlong/30\n  rotate: false\n  xy: 115, 228\n  size: 111, 111\n  orig: 111, 111\n  offset: 0, 0\n  index: -1\nlong/31\n  rotate: false\n  xy: 228, 341\n  size: 111, 111\n  orig: 111, 111\n  offset: 0, 0\n  index: -1\nlong/32\n  rotate: false\n  xy: 341, 454\n  size: 111, 111\n  orig: 111, 111\n  offset: 0, 0\n  index: -1\nlong/33\n  rotate: false\n  xy: 454, 567\n  size: 111, 111\n  orig: 111, 111\n  offset: 0, 0\n  index: -1\nlong/34\n  rotate: false\n  xy: 567, 680\n  size: 111, 111\n  orig: 111, 111\n  offset: 0, 0\n  index: -1\nlong/35\n  rotate: false\n  xy: 680, 793\n  size: 111, 111\n  orig: 111, 111\n  offset: 0, 0\n  index: -1\nlong/36\n  rotate: false\n  xy: 793, 906\n  size: 111, 111\n  orig: 111, 111\n  offset: 0, 0\n  index: -1\nlong/37\n  rotate: false\n  xy: 2, 2\n  size: 111, 111\n  orig: 111, 111\n  offset: 0, 0\n  index: -1\nlong/38\n  rotate: false\n  xy: 115, 115\n  size: 111, 111\n  orig: 111, 111\n  offset: 0, 0\n  index: -1\nlong/39\n  rotate: false\n  xy: 228, 228\n  size: 111, 111\n  orig: 111, 111\n  offset: 0, 0\n  index: -1\nlong/4\n  rotate: false\n  xy: 2, 680\n  size: 111, 111\n  orig: 111, 111\n  offset: 0, 0\n  index: -1\nlong/40\n  rotate: false\n  xy: 341, 341\n  size: 111, 111\n  orig: 111, 111\n  offset: 0, 0\n  index: -1\nlong/41\n  rotate: false\n  xy: 454, 454\n  size: 111, 111\n  orig: 111, 111\n  offset: 0, 0\n  index: -1\nlong/5\n  rotate: false\n  xy: 115, 793\n  size: 111, 111\n  orig: 111, 111\n  offset: 0, 0\n  index: -1\nlong/6\n  rotate: false\n  xy: 228, 906\n  size: 111, 111\n  orig: 111, 111\n  offset: 0, 0\n  index: -1\nlong/7\n  rotate: false\n  xy: 2, 567\n  size: 111, 111\n  orig: 111, 111\n  offset: 0, 0\n  index: -1\nlong/8\n  rotate: false\n  xy: 115, 680\n  size: 111, 111\n  orig: 111, 111\n  offset: 0, 0\n  index: -1\nlong/9\n  rotate: false\n  xy: 228, 793\n  size: 111, 111\n  orig: 111, 111\n  offset: 0, 0\n  index: -1\n",
  "textures": [
    {
      "__uuid__": "46G7sXFR9Cd5/GycENntHh"
    }
  ],
  "textureNames": [
    "LHD_longying_guang.png"
  ]
}